chatool/__init__.py
chatool/version.py
chatool-0.0.0.dist-info/LICENSE
chatool-0.0.0.dist-info/METADATA
chatool-0.0.0.dist-info/WHEEL
chatool-0.0.0.dist-info/top_level.txt
chatool-0.0.0.dist-info/RECORD
