Metadata-Version: 2.1
Name: chatool
Version: 0.0.0
Summary: Chat Tools
Author-email: Jiau Zhang <jiauzhang@163.com>
Project-URL: Homepage, https://github.com/jiauzhang/chatool
Keywords: Deep Learning,Artificial Intelligence
Classifier: Intended Audience :: Developers
Classifier: Topic :: Scientific/Engineering :: Artificial Intelligence
Classifier: License :: OSI Approved :: GNU General Public License v2 (GPLv2)
Classifier: Programming Language :: Python :: 3.8
Requires-Python: >=3.8
License-File: LICENSE
Requires-Dist: chatchat
